enverge_nativeauthenticator/__init__.py
enverge_nativeauthenticator/enverge_nativeauthenticator.py
enverge_nativeauthenticator/handlers.py
enverge_nativeauthenticator/orm.py
enverge_nativeauthenticator/media/.DS_Store
enverge_nativeauthenticator/media/images/enverge-logo-only.svg
enverge_nativeauthenticator/media/images/enverge-logo.svg
enverge_nativeauthenticator/templates/page.html
enverge_nativeauthenticator/templates/signup.html
jupyterhub_enverge_nativeauthenticator-0.0.6.dist-info/METADATA
jupyterhub_enverge_nativeauthenticator-0.0.6.dist-info/WHEEL
jupyterhub_enverge_nativeauthenticator-0.0.6.dist-info/entry_points.txt
jupyterhub_enverge_nativeauthenticator-0.0.6.dist-info/top_level.txt
jupyterhub_enverge_nativeauthenticator-0.0.6.dist-info/RECORD
