Metadata-Version: 2.4
Name: jupyterhub-enverge-nativeauthenticator
Version: 0.0.6
Summary: JupyterHub Enverge Native Authenticator
Home-page: https://github.com/Enverge-Labs/enverge_nativeauthenticator
Author: Tudor Munteanu
Author-email: tudor@enverge.ai
License: 3 Clause BSD
Requires-Python: >=3.9
Requires-Dist: jupyterhub>=4.1.6
Requires-Dist: bcrypt
Requires-Dist: onetimepass
Requires-Dist: jupyterhub-nativeauthenticator
Provides-Extra: test
Requires-Dist: notebook>=6.4.1; extra == "test"
Requires-Dist: pytest; extra == "test"
Requires-Dist: pytest-asyncio; extra == "test"
Requires-Dist: pytest-cov; extra == "test"
Dynamic: author
Dynamic: author-email
Dynamic: description
Dynamic: description-content-type
Dynamic: home-page
Dynamic: license
Dynamic: provides-extra
Dynamic: requires-dist
Dynamic: requires-python
Dynamic: summary
